[
  {
    "name": "Crew",
    "dialogue": "Captain Cecil, we are about to arrive!",
    "id": 1
  },
  {
    "name": "Cecil",
    "dialogue": "Good.",
    "id": 2
  },
  {
    "name": "Crew",
    "dialogue": "Why are we robbing crystals from innocent people?",
    "id": 3
  },
  {
    "name": "Crew",
    "dialogue": "That's our duty.",
    "id": 4
  },
  {
    "name": "Crew",
    "dialogue": "Do we really have to keep doing this?",
    "id": 5
  },
  {
    "name": "Crew",
    "dialogue": "Give us the Crystal of Water!",
    "id": 6
  },
  {
    "name": "Elder",
    "dialogue": "What have we done?",
    "id": 7
  },
  {
    "name": "Cecil",
    "dialogue": "The crystal or your life!",
    "id": 8
  },
  {
    "name": "Black Wizard",
    "dialogue": "Never!",
    "id": 9
  },
  {
    "name": "Cecil",
    "dialogue": "Then, take the crystal by force!",
    "id": 10
  },
  {
    "name": "Black Wizard",
    "dialogue": "WAAAH!",
    "id": 11
  },
  {
    "name": "White Wizard",
    "dialogue": "No! Don't!",
    "id": 12
  },
  {
    "name": "Crew",
    "dialogue": "Dare to defy us?",
    "id": 13
  },
  {
    "name": "White Wizard",
    "dialogue": "ARRRGH!",
    "id": 14
  },
  {
    "name": "Elder",
    "dialogue": "My! All right... Take the crystal!",
    "id": 15
  },
  {
    "name": "Crew",
    "dialogue": "You should have said it earlier!",
    "id": 16
  },
  {
    "name": "Elder",
    "dialogue": "Why is the King of Baron doing this? Why do you pursue the crystals so eagerly?",
    "id": 17
  },
  {
    "name": "Cecil",
    "dialogue": "......",
    "id": 18
  },
  {
    "name": "Crew",
    "dialogue": "We take pride in being members of the Red Wings! Looting is out of the question!",
    "id": 19
  },
  {
    "name": "Cecil",
    "dialogue": "Stop it!",
    "id": 20
  },
  {
    "name": "Crew",
    "dialogue": "Captain!",
    "id": 21
  },
  {
    "name": "Crew",
    "dialogue": "We can't stand doing this anymore!",
    "id": 22
  },
  {
    "name": "Cecil",
    "dialogue": "Listen! Possessing the crystal is an essential factor for our prosperity. Moreover, His Majesty judged that Mysidians know too much about the secret of the crystal. We are the Red Wings, the air force of the Kingdom Baron! The Royal Command is absolute. Crew: Captain!",
    "id": 23
  },
  {
    "name": "Crew",
    "dialogue": "Monsters!!",
    "id": 24
  },
  {
    "name": "Cecil",
    "dialogue": "Take up fighting positions!",
    "id": 25
  },
  {
    "name": "Crew",
    "dialogue": "Ouch!",
    "id": 26
  },
  {
    "name": "Cecil",
    "dialogue": "You Okay?",
    "id": 27
  },
  {
    "name": "Crew",
    "dialogue": "More coming!",
    "id": 28
  },
  {
    "name": "Cecil",
    "dialogue": "Watch out!",
    "id": 29
  },
  {
    "name": "Cecil",
    "dialogue": "Everyone okay?",
    "id": 30
  },
  {
    "name": "Crew",
    "dialogue": "Yes, sir!",
    "id": 31
  },
  {
    "name": "Crew",
    "dialogue": "But there are too many monsters these days...",
    "id": 32
  },
  {
    "name": "Crew",
    "dialogue": "Too many, agreed.",
    "id": 33
  },
  {
    "name": "Cecil",
    "dialogue": "What's happening?",
    "id": 34
  },
  {
    "name": "Crew",
    "dialogue": "We are over Baron!",
    "id": 35
  },
  {
    "name": "Cecil",
    "dialogue": "Make a landing.",
    "id": 36
  },
  {
    "name": "Baigan",
    "dialogue": "Oh, Cecil! Is it the Crystal of Water?",
    "id": 37
  },
  {
    "name": "Cecil",
    "dialogue": "But Mysidians were so helpless.",
    "id": 38
  },
  {
    "name": "Baigan",
    "dialogue": "What are you trying to say? This way, Cecil.",
    "id": 39
  },
  {
    "name": "Baigan",
    "dialogue": "Please wait here.",
    "id": 40
  },
  {
    "name": "Baigan",
    "dialogue": "Your Majesty! I'm afraid Cecil has developed quite a rebellious air.",
    "id": 41
  },
  {
    "name": "King",
    "dialogue": "Truly!? Well done, Baigan! We must do something. Call him in! Baigan: Yes, Your Majesty.",
    "id": 42
  },
  {
    "name": "Baigan",
    "dialogue": "Cecil!  His Majesty summons you. Please come in.",
    "id": 43
  },
  {
    "name": "King",
    "dialogue": "We thank you for successfully completing the mission. Now, where is it?",
    "id": 44
  },
  {
    "name": "Cecil",
    "dialogue": "Here, My Liege. Hand over the crystal.",
    "id": 45
  },
  {
    "name": "Baigan",
    "dialogue": "Real crystal...",
    "id": 46
  },
  {
    "name": "King",
    "dialogue": "Good!  Cecil...... You may leave now.",
    "id": 47
  },
  {
    "name": "Cecil",
    "dialogue": "Your Majesty!",
    "id": 48
  },
  {
    "name": "King",
    "dialogue": "W... What?",
    "id": 49
  },
  {
    "name": "Baigan",
    "dialogue": "W... What is it?",
    "id": 50
  },
  {
    "name": "Cecil",
    "dialogue": "We do not understand the meaning of taking crystals away from honest people.",
    "id": 51
  },
  {
    "name": "King",
    "dialogue": "Disobeying me?",
    "id": 52
  },
  {
    "name": "Cecil",
    "dialogue": "No, I don't.",
    "id": 53
  },
  {
    "name": "King",
    "dialogue": "We do know of your discontent, Cecil. If you cannot trust me, I can no longer place the Red Wings in your command. You are dismissed from your post!",
    "id": 54
  },
  {
    "name": "Cecil",
    "dialogue": "Your Majesty!",
    "id": 55
  },
  {
    "name": "King",
    "dialogue": "Go and hunt the Summoned Monsters of the Misty Valley! And... Take this Package to the Village Mist. You may depart tomorrow morning!",
    "id": 56
  },
  {
    "name": "Kain",
    "dialogue": "Your Majesty!",
    "id": 57
  },
  {
    "name": "Kain",
    "dialogue": "Cecil didn't...",
    "id": 58
  },
  {
    "name": "King",
    "dialogue": "If you're concerned about Cecil that much, go with him, Kain!",
    "id": 59
  },
  {
    "name": "Cecil",
    "dialogue": "Your Majesty!",
    "id": 60
  },
  {
    "name": "King",
    "dialogue": "Now! Leave with the Package!",
    "id": 61
  }
]